gshare_tester.v
module bimoded
(output reg clk_i, 
output reg reset_i, 
output reg [63:0] branch_address, 
output reg real_ton
);

always #1 clk_i = !clk_i;
initial 
begin
    clk_i=0;
    reset_i = 1;
    #50
    reset_i = 0;
    // Simulación 1
    #50;
    branch_address = 64'h0000_54A1_0000_0001;
    real_ton = 0;
    #50;

    branch_address = 64'h0000_0000_0000_000B;
    real_ton = 1;
    #50;

    branch_address = 64'h0000_0000_0000_0CBA;
    real_ton = 0;
    #50;

    branch_address = 64'h0000_0000_0000_BBBB;
    real_ton = 1;
    #50;
    $finish;
    end
    
 
endmodule

Gshare.v
module bimode(
    input clk_i,
    input reset_i,
    input [63:0] branch_address,     //64 bits branch address.
    input real_ton,
    output reg prediction
);
    //variables internas.
    reg [7:0] global_history;      //8 bits history. Shift register.
    wire [7:0] index;             //index generated by xor
    wire [7:0] index2;           //index para selector 
    integer i;
    reg [31:0] aciertos, total;
    reg [31:0] porcentaje_de_aciertos;

    //Tablas PTH
    reg [1:0] selection_pht [0:255];         //PHT 2 bits (2bc), and 64 bits lenght (global_history bits)^2 
    reg [1:0] taken_pht [0:255];  
    reg [1:0] not_taken_pht [0:255];  

    //XOR para index.
    assign index = global_history ^ branch_address[7:0]; // index para taken y no_taken pht
    //index de selection solo depende de branch address
    assign index2 = branch_address[7:0]; // index para selection_pht
    
    always@(posedge clk_i) begin
        if(reset_i)begin
            for (i = 0; i < 255; i = i + 1) begin 
                taken_pht[i] <= 2'b01;      // estado inicial "neutro" = weak not taken
                not_taken_pht[i] <= 2'b01;  // estado inicial "neutro" = weak not taken
                selection_pht[i] <= 2'b01;  // estado inicial "neutro" = weak not taken
                aciertos = 0;
                total=0;
            end
            global_history <= 8'b0; // y el historial esta en NT por default.
        end


        else begin
            //eleccion
            if(selection_pht[index2] > 2'b01)begin //si taken_pht es wt o st se va a taken_pht
                if(taken_pht[index]>2'b01)begin  //si taken_pht decide que se tome, porque es weak take o st
                    prediction = 1'b1;    //take
                end
                else begin
                    prediction = 1'b0;       //si la tabla taken_pht decide que no se toma
                end
            end

            else begin  // sino, se va a la tabla de not_taken y ve que decide not_taken
                if(not_taken_pht[index]>2'b01)begin  //si not_taken_pht decide que se tome, porque es weak take o st
                    prediction = 1'b0;       //not take
                end
                else begin
                    prediction = 1'b1;       //si la tabla no_taken_pht decide que no se toma
                end
            end


            //cambios a partir del resultado real.
            // Actualización predicción.
            if (real_ton == prediction) begin // Predicción correcta. Aumentar confianza (saturadamente)
                aciertos=aciertos+1;
                if (selection_pht[index2] != 2'b11) begin
                    selection_pht[index2] <= selection_pht[index2] + 1; // Incrementar si no está saturado.
                end
                if(taken_pht[index] != 2'b11) //contador saturado
                    taken_pht[index] <= taken_pht[index]+1;
            end
            else begin
                // Predicción incorrecta.
                //error = error+1;
                if (selection_pht[index2] != 2'b00) begin
                    selection_pht[index2] <= selection_pht[index2] - 1; // Decrementar si no está saturado.
                end
                if(not_taken_pht[index] != 2'b11) //contador saturado
                    not_taken_pht[index] <= not_taken_pht[index]+1;
            end
            total <= total + 1;
            


            
            //porcentaje de aciertos
            if (total > 0) begin
                porcentaje_de_aciertos <= (aciertos / total) * 100.0;
            end else begin
                porcentaje_de_aciertos = 0.0; // Prevenir división por cero.
            end

            //actualizacion de la historia global shift(FIFO)
            global_history <= {global_history[6:0], real_ton};

            //BTB
            



        end
    end

endmodule

gshare_tb.v
`include "Gshare.v"
`include "gshare_tester.v"

module gs_tb;
    // señales para el testbench
    wire clk_i;
    wire reset_i;
    wire [63:0] branch_address;
    wire real_ton;
    wire prediction;
    wire porcentaje_de_aciertos;

    initial 
    begin
        $dumpfile("sim.vcd");
        $dumpvars(-1, uut);
        $monitor("Time: %0d | Addr: %h | Taken: %b | Prediction: %b | Global History: %b | porcentaje de aciertos: %",
                 $time, branch_address, real_ton, prediction, uut.global_history,porcentaje_de_aciertos);
        
    end
    
    bimode uut (
        .clk_i(clk_i),
        .reset_i(reset_i),
        .branch_address(branch_address),
        .real_ton(real_ton),
        .prediction(prediction)
    );

    bimoded uuut(
        .clk_i(clk_i),
        .reset_i(reset_i),
        .branch_address(branch_address),
        .real_ton(real_ton)
    );

endmodule

sim.vcd
$date
	Wed Sep 11 02:17:58 2024
$end
$version
	Icarus Verilog
$end
$timescale
	1s
$end
$scope module gs_tb $end
$scope module uut $end
$var wire 8 ! index [7:0] $end
$var wire 1 " reset_i $end
$var wire 1 # real_ton $end
$var wire 8 $ index2 [7:0] $end
$var wire 1 % clk_i $end
$var wire 64 & branch_address [63:0] $end
$var reg 32 ' aciertos [31:0] $end
$var reg 8 ( global_history [7:0] $end
$var reg 32 ) porcentaje_de_aciertos [31:0] $end
$var reg 1 * prediction $end
$var reg 32 + total [31:0] $end
$var integer 32 , i [31:0] $end
$upscope $end
$upscope $end
$enddefinitions $end
#0
$dumpvars
bx ,
bx +
x*
bx )
bx (
bx '
bx &
0%
bx $
x#
1"
bx !
$end
#1
b0 (
b0 +
b0 '
b11111111 ,
1%
#2
0%
#3
b11111111 ,
1%
#4
0%
#5
b11111111 ,
1%
#6
0%
#7
b11111111 ,
1%
#8
0%
#9
b11111111 ,
1%
#10
0%
#11
b11111111 ,
1%
#12
0%
#13
b11111111 ,
1%
#14
0%
#15
b11111111 ,
1%
#16
0%
#17
b11111111 ,
1%
#18
0%
#19
b11111111 ,
1%
#20
0%
#21
b11111111 ,
1%
#22
0%
#23
b11111111 ,
1%
#24
0%
#25
b11111111 ,
1%
#26
0%
#27
b11111111 ,
1%
#28
0%
#29
b11111111 ,
1%
#30
0%
#31
b11111111 ,
1%
#32
0%
#33
b11111111 ,
1%
#34
0%
#35
b11111111 ,
1%
#36
0%
#37
b11111111 ,
1%
#38
0%
#39
b11111111 ,
1%
#40
0%
#41
b11111111 ,
1%
#42
0%
#43
b11111111 ,
1%
#44
0%
#45
b11111111 ,
1%
#46
0%
#47
b11111111 ,
1%
#48
0%
#49
b11111111 ,
1%
#50
0%
0"
#51
b0x (
b1 +
b0 )
1*
1%
#52
0%
#53
b0xx (
b10 +
1%
#54
0%
#55
b0xxx (
b11 +
1%
#56
0%
#57
b0xxxx (
b100 +
1%
#58
0%
#59
b0xxxxx (
b101 +
1%
#60
0%
#61
b0xxxxxx (
b110 +
1%
#62
0%
#63
b0xxxxxxx (
b111 +
1%
#64
0%
#65
bx (
b1000 +
1%
#66
0%
#67
b1001 +
1%
#68
0%
#69
b1010 +
1%
#70
0%
#71
b1011 +
1%
#72
0%
#73
b1100 +
1%
#74
0%
#75
b1101 +
1%
#76
0%
#77
b1110 +
1%
#78
0%
#79
b1111 +
1%
#80
0%
#81
b10000 +
1%
#82
0%
#83
b10001 +
1%
#84
0%
#85
b10010 +
1%
#86
0%
#87
b10011 +
1%
#88
0%
#89
b10100 +
1%
#90
0%
#91
b10101 +
1%
#92
0%
#93
b10110 +
1%
#94
0%
#95
b10111 +
1%
#96
0%
#97
b11000 +
1%
#98
0%
#99
b11001 +
1%
#100
b1 $
0%
0#
b10101001010000100000000000000000000000000000001 &
#101
bx1 !
bx0 (
b11010 +
1%
#102
0%
#103
bx01 !
bx00 (
b11011 +
1%
#104
0%
#105
bx001 !
bx000 (
b11100 +
1%
#106
0%
#107
bx0001 !
bx0000 (
b11101 +
1%
#108
0%
#109
bx00001 !
bx00000 (
b11110 +
1%
#110
0%
#111
bx000001 !
bx000000 (
b11111 +
1%
#112
0%
#113
bx0000001 !
bx0000000 (
b100000 +
1%
#114
0%
#115
b1 !
b0 (
b100001 +
1%
#116
0%
#117
b100010 +
1%
#118
0%
#119
b100011 +
b1 '
0*
1%
#120
0%
#121
b100100 +
b10 '
1%
#122
0%
#123
b100101 +
1*
1%
#124
0%
#125
b100110 +
b11 '
0*
1%
#126
0%
#127
b100111 +
1*
1%
#128
0%
#129
b101000 +
b100 '
0*
1%
#130
0%
#131
b101001 +
1*
1%
#132
0%
#133
b101010 +
b101 '
0*
1%
#134
0%
#135
b101011 +
1*
1%
#136
0%
#137
b101100 +
b110 '
0*
1%
#138
0%
#139
b101101 +
1*
1%
#140
0%
#141
b101110 +
b111 '
0*
1%
#142
0%
#143
b101111 +
1*
1%
#144
0%
#145
b110000 +
b1000 '
0*
1%
#146
0%
#147
b110001 +
1*
1%
#148
0%
#149
b110010 +
b1001 '
0*
1%
#150
b1011 !
b1011 $
0%
1#
b1011 &
#151
b1010 !
b1 (
b110011 +
b1010 '
1*
1%
#152
0%
#153
b1000 !
b11 (
b110100 +
0*
1%
#154
0%
#155
b1100 !
b111 (
b110101 +
b1011 '
1*
1%
#156
0%
#157
b100 !
b1111 (
b110110 +
0*
1%
#158
0%
#159
b10100 !
b11111 (
b110111 +
b1100 '
1*
1%
#160
0%
#161
b110100 !
b111111 (
b111000 +
0*
1%
#162
0%
#163
b1110100 !
b1111111 (
b111001 +
b1101 '
1*
1%
#164
0%
#165
b11110100 !
b11111111 (
b111010 +
0*
1%
#166
0%
#167
b111011 +
b1110 '
1*
1%
#168
0%
#169
b111100 +
b1111 '
1%
#170
0%
#171
b111101 +
b10000 '
1%
#172
0%
#173
b111110 +
b10001 '
1%
#174
0%
#175
b111111 +
b10010 '
1%
#176
0%
#177
b1000000 +
b10011 '
1%
#178
0%
#179
b1000001 +
b10100 '
1%
#180
0%
#181
b1000010 +
b10101 '
1%
#182
0%
#183
b1000011 +
b10110 '
1%
#184
0%
#185
b1000100 +
b10111 '
1%
#186
0%
#187
b1000101 +
b11000 '
1%
#188
0%
#189
b1000110 +
b11001 '
1%
#190
0%
#191
b1000111 +
b11010 '
1%
#192
0%
#193
b1001000 +
b11011 '
1%
#194
0%
#195
b1001001 +
b11100 '
1%
#196
0%
#197
b1001010 +
b11101 '
1%
#198
0%
#199
b1001011 +
b11110 '
1%
#200
b1000101 !
b10111010 $
0%
0#
b110010111010 &
#201
b1000100 !
b11111110 (
b1001100 +
1%
#202
0%
#203
b1000110 !
b11111100 (
b1001101 +
1%
#204
0%
#205
b1000010 !
b11111000 (
b1001110 +
1%
#206
0%
#207
b1001010 !
b11110000 (
b1001111 +
1%
#208
0%
#209
b1011010 !
b11100000 (
b1010000 +
1%
#210
0%
#211
b1111010 !
b11000000 (
b1010001 +
1%
#212
0%
#213
b111010 !
b10000000 (
b1010010 +
1%
#214
0%
#215
b10111010 !
b0 (
b1010011 +
1%
#216
0%
#217
b1010100 +
1%
#218
0%
#219
b1010101 +
b11111 '
0*
1%
#220
0%
#221
b1010110 +
b100000 '
1%
#222
0%
#223
b1010111 +
1*
1%
#224
0%
#225
b1011000 +
b100001 '
0*
1%
#226
0%
#227
b1011001 +
1*
1%
#228
0%
#229
b1011010 +
b100010 '
0*
1%
#230
0%
#231
b1011011 +
1*
1%
#232
0%
#233
b1011100 +
b100011 '
0*
1%
#234
0%
#235
b1011101 +
1*
1%
#236
0%
#237
b1011110 +
b100100 '
0*
1%
#238
0%
#239
b1011111 +
1*
1%
#240
0%
#241
b1100000 +
b100101 '
0*
1%
#242
0%
#243
b1100001 +
1*
1%
#244
0%
#245
b1100010 +
b100110 '
0*
1%
#246
0%
#247
b1100011 +
1*
1%
#248
0%
#249
b1100100 +
b100111 '
0*
1%
#250
b10111011 !
b10111011 $
0%
1#
b1011101110111011 &
#251
b10111010 !
b1 (
b1100101 +
b101000 '
1*
1%
#252
0%
#253
b10111000 !
b11 (
b1100110 +
b101001 '
1%
#254
0%
#255
b10111100 !
b111 (
b1100111 +
0*
1%
#256
0%
#257
b10110100 !
b1111 (
b1101000 +
1%
#258
0%
#259
b10100100 !
b11111 (
b1101001 +
b101010 '
1*
1%
#260
0%
#261
b10000100 !
b111111 (
b1101010 +
0*
1%
#262
0%
#263
b11000100 !
b1111111 (
b1101011 +
b101011 '
1*
1%
#264
0%
#265
b1000100 !
b11111111 (
b1101100 +
0*
1%
#266
0%
#267
b1101101 +
1%
#268
0%
#269
b1101110 +
1%
#270
0%
#271
b1101111 +
1%
#272
0%
#273
b1110000 +
1%
#274
0%
#275
b1110001 +
1%
#276
0%
#277
b1110010 +
1%
#278
0%
#279
b1110011 +
1%
#280
0%
#281
b1110100 +
1%
#282
0%
#283
b1110101 +
1%
#284
0%
#285
b1110110 +
1%
#286
0%
#287
b1110111 +
1%
#288
0%
#289
b1111000 +
1%
#290
0%
#291
b1111001 +
1%
#292
0%
#293
b1111010 +
1%
#294
0%
#295
b1111011 +
1%
#296
0%
#297
b1111100 +
1%
#298
0%
#299
b1111101 +
1%
