gshare_tester.v
module bimoded
(output reg clk, 
output reg rst, 
output reg [63:0] branch_address, 
output reg real_ton
);

always #1 clk = !clk;
initial 
begin
    clk=0;
    rst = 1;
    #50
    rst = 0;
    // Simulación 1
    #50;
    branch_address = 64'h0000_54A1_0000_0001;
    real_ton = 0;
    #50;

    branch_address = 64'h0000_0000_0000_000B;
    real_ton = 1;
    #50;

    branch_address = 64'h0000_0000_0000_0CBA;
    real_ton = 0;
    #50;
    
    branch_address = 64'h0000_0000_0000_BBBB;
    real_ton = 1;
    #50;
    $finish;
    end
    
 
endmodule

Gshare.v
module bimode(
    input clk,
    input rst,
    input [63:0] branch_address,     //64 bits branch address.
    input real_ton,
    output reg prediction
);
    //variables internas.
    reg [7:0] global_history;      //8 bits history. Shift register.
    wire [7:0] index;             //index generated by xor
    wire [7:0] index2; 
    integer i;
    reg aciertos, total;
    real porcentaje_de_aciertos;

    //Tablas PTH
    reg [1:0] selection_pht [0:255];         //PHT 2 bits (2bc), and 64 bits lenght (global_history bits)^2 
    reg [1:0] taken_pht [0:255];  
    reg [1:0] not_taken_pht [0:255];  

    //XOR para index.
    assign index = global_history ^ branch_address[7:0]; // index para taken y no_taken pht
    //index de seleccion solo depende de branch address
    assign index2 = branch_address[7:0]; // index para selection_pht
    
    always@(posedge clk or posedge rst) begin
        if(rst)begin
            for (i = 0; i < 255; i = i + 1) begin 
                taken_pht[i] <= 2'b01;      // estado inicial "neutro" = weak not taken
                not_taken_pht[i] <= 2'b01;  // estado inicial "neutro" = weak not taken
                selection_pht[i] <= 2'b01;  // estado inicial "neutro" = weak not taken
                aciertos = 0;
                total=0;
            end
            global_history <= 8'b0; // y el historial esta en NT por default.
        end


        else begin
            //eleccion
            if(selection_pht[index2] > 2'b01)begin //si taken_pht es wt o st se va a taken_pht
                if(taken_pht[index]>2'b01)begin  //si taken_pht decide que se tome, porque es weak take o st
                    prediction = 1'b1;    //take
                end
                else begin
                    prediction = 1'b0;       //si la tabla taken_pht decide que no se toma
                end
            end

            else begin  // sino, se va a la tabla de not_taken y ve que decide not_taken
                if(not_taken_pht[index]>2'b01)begin  //si not_taken_pht decide que se tome, porque es weak take o st
                    prediction = 1'b0;       //not take
                end
                else begin
                    prediction = 1'b1;       //si la tabla no_taken_pht decide que no se toma
                end
            end


            //cambios a partir del resultado real.
            // Actualización predicción.
            if (real_ton == prediction) begin // Predicción correcta. Aumentar confianza (saturadamente)
                aciertos=aciertos+1;
                total = total+1;
                if (selection_pht[index2] != 2'b11) begin
                    selection_pht[index2] <= selection_pht[index2] + 1; // Incrementar si no está saturado.
                end
                if(taken_pht[index] != 2'b11) //contador saturado
                    taken_pht[index] <= taken_pht[index]+1;
            end
            else begin
                // Predicción incorrecta.
                total=total+1;
                if (selection_pht[index2] != 2'b00) begin
                    selection_pht[index2] <= selection_pht[index2] - 1; // Decrementar si no está saturado.
                end
                if(not_taken_pht[index] != 2'b11) //contador saturado
                    not_taken_pht[index] <= not_taken_pht[index]+1;
            end

            
            //porcentaje de aciertos
            if (total > 0) begin
                porcentaje_de_aciertos <= (aciertos / total) * 100.0;
            end else begin
                porcentaje_de_aciertos <= 0.0; // Prevenir división por cero.
            end

            //actualizacion de la historia global shift(FIFO)
            global_history <= {global_history[6:0], real_ton};

            //BTB
            



        end
    end

endmodule

gshare_tb.v
`include "Gshare.v"
`include "gshare_tester.v"

module gs_tb;
    // señales para el testbench
    wire clk;
    wire rst;
    wire [63:0] branch_address;
    wire real_ton;
    wire prediction;
    wire porcentaje_de_aciertos;

    initial 
    begin
        $dumpfile("sim.vcd");
        $dumpvars(-1, uut);
        $monitor("Time: %0d | Addr: %h | Taken: %b | Prediction: %b | Global History: %b | porcentaje de aciertos: %",
                 $time, branch_address, real_ton, prediction, uut.global_history,porcentaje_de_aciertos);
        
    end
    
    bimode uut (
        .clk(clk),
        .rst(rst),
        .branch_address(branch_address),
        .real_ton(real_ton),
        .prediction(prediction)
    );

    bimoded uuut(
        .clk(clk),
        .rst(rst),
        .branch_address(branch_address),
        .real_ton(real_ton)
    );

endmodule

sim.vcd
$date
	Wed Sep 11 00:17:52 2024
$end
$version
	Icarus Verilog
$end
$timescale
	1s
$end
$scope module gs_tb $end
$scope module uut $end
$var wire 8 ! index [7:0] $end
$var wire 1 " rst $end
$var wire 1 # real_ton $end
$var wire 8 $ index2 [7:0] $end
$var wire 1 % clk $end
$var wire 64 & branch_address [63:0] $end
$var reg 1 ' aciertos $end
$var reg 8 ( global_history [7:0] $end
$var reg 1 ) prediction $end
$var reg 1 * total $end
$var integer 32 + i [31:0] $end
$var real 1 , porcentaje_de_aciertos $end
$upscope $end
$upscope $end
$enddefinitions $end
#0
$dumpvars
r0 ,
b11111111 +
0*
x)
b0 (
0'
bx &
0%
bx $
x#
1"
bx !
$end
#1
b11111111 +
1%
#2
0%
#3
b11111111 +
1%
#4
0%
#5
b11111111 +
1%
#6
0%
#7
b11111111 +
1%
#8
0%
#9
b11111111 +
1%
#10
0%
#11
b11111111 +
1%
#12
0%
#13
b11111111 +
1%
#14
0%
#15
b11111111 +
1%
#16
0%
#17
b11111111 +
1%
#18
0%
#19
b11111111 +
1%
#20
0%
#21
b11111111 +
1%
#22
0%
#23
b11111111 +
1%
#24
0%
#25
b11111111 +
1%
#26
0%
#27
b11111111 +
1%
#28
0%
#29
b11111111 +
1%
#30
0%
#31
b11111111 +
1%
#32
0%
#33
b11111111 +
1%
#34
0%
#35
b11111111 +
1%
#36
0%
#37
b11111111 +
1%
#38
0%
#39
b11111111 +
1%
#40
0%
#41
b11111111 +
1%
#42
0%
#43
b11111111 +
1%
#44
0%
#45
b11111111 +
1%
#46
0%
#47
b11111111 +
1%
#48
0%
#49
b11111111 +
1%
#50
0%
0"
#51
b0x (
1*
1)
1%
#52
0%
#53
b0xx (
0*
1%
#54
0%
#55
b0xxx (
1*
1%
#56
0%
#57
b0xxxx (
0*
1%
#58
0%
#59
b0xxxxx (
1*
1%
#60
0%
#61
b0xxxxxx (
0*
1%
#62
0%
#63
b0xxxxxxx (
1*
1%
#64
0%
#65
bx (
0*
1%
#66
0%
#67
1*
1%
#68
0%
#69
0*
1%
#70
0%
#71
1*
1%
#72
0%
#73
0*
1%
#74
0%
#75
1*
1%
#76
0%
#77
0*
1%
#78
0%
#79
1*
1%
#80
0%
#81
0*
1%
#82
0%
#83
1*
1%
#84
0%
#85
0*
1%
#86
0%
#87
1*
1%
#88
0%
#89
0*
1%
#90
0%
#91
1*
1%
#92
0%
#93
0*
1%
#94
0%
#95
1*
1%
#96
0%
#97
0*
1%
#98
0%
#99
1*
1%
#100
b1 $
0%
0#
b10101001010000100000000000000000000000000000001 &
#101
bx1 !
bx0 (
0*
1%
#102
0%
#103
bx01 !
bx00 (
1*
1%
#104
0%
#105
bx001 !
bx000 (
0*
1%
#106
0%
#107
bx0001 !
bx0000 (
1*
1%
#108
0%
#109
bx00001 !
bx00000 (
0*
1%
#110
0%
#111
bx000001 !
bx000000 (
1*
1%
#112
0%
#113
bx0000001 !
bx0000000 (
0*
1%
#114
0%
#115
b1 !
b0 (
1*
1%
#116
0%
#117
0*
1%
#118
0%
#119
r100 ,
1*
1'
0)
1%
#120
0%
#121
r0 ,
0*
0'
1%
#122
0%
#123
1*
1)
1%
#124
0%
#125
0*
1'
0)
1%
#126
0%
#127
r100 ,
1*
1)
1%
#128
0%
#129
r0 ,
0*
0'
0)
1%
#130
0%
#131
1*
1)
1%
#132
0%
#133
0*
1'
0)
1%
#134
0%
#135
r100 ,
1*
1)
1%
#136
0%
#137
r0 ,
0*
0'
0)
1%
#138
0%
#139
1*
1)
1%
#140
0%
#141
0*
1'
0)
1%
#142
0%
#143
r100 ,
1*
1)
1%
#144
0%
#145
r0 ,
0*
0'
0)
1%
#146
0%
#147
1*
1)
1%
#148
0%
#149
0*
1'
0)
1%
#150
b1011 !
b1011 $
0%
1#
b1011 &
#151
b1010 !
b1 (
1*
0'
1)
1%
#152
0%
#153
b1000 !
b11 (
0*
0)
1%
#154
0%
#155
b1100 !
b111 (
r100 ,
1*
1'
1)
1%
#156
0%
#157
b100 !
b1111 (
r0 ,
0*
0)
1%
#158
0%
#159
b10100 !
b11111 (
1*
0'
1)
1%
#160
0%
#161
b110100 !
b111111 (
0*
0)
1%
#162
0%
#163
b1110100 !
b1111111 (
r100 ,
1*
1'
1)
1%
#164
0%
#165
b11110100 !
b11111111 (
r0 ,
0*
0)
1%
#166
0%
#167
1*
0'
1)
1%
#168
0%
#169
0*
1'
1%
#170
0%
#171
1*
0'
1%
#172
0%
#173
0*
1'
1%
#174
0%
#175
1*
0'
1%
#176
0%
#177
0*
1'
1%
#178
0%
#179
1*
0'
1%
#180
0%
#181
0*
1'
1%
#182
0%
#183
1*
0'
1%
#184
0%
#185
0*
1'
1%
#186
0%
#187
1*
0'
1%
#188
0%
#189
0*
1'
1%
#190
0%
#191
1*
0'
1%
#192
0%
#193
0*
1'
1%
#194
0%
#195
1*
0'
1%
#196
0%
#197
0*
1'
1%
#198
0%
#199
1*
0'
1%
#200
b1000101 !
b10111010 $
0%
0#
b110010111010 &
#201
b1000100 !
b11111110 (
0*
1%
#202
0%
#203
b1000110 !
b11111100 (
1*
1%
#204
0%
#205
b1000010 !
b11111000 (
0*
1%
#206
0%
#207
b1001010 !
b11110000 (
1*
1%
#208
0%
#209
b1011010 !
b11100000 (
0*
1%
#210
0%
#211
b1111010 !
b11000000 (
1*
1%
#212
0%
#213
b111010 !
b10000000 (
0*
1%
#214
0%
#215
b10111010 !
b0 (
1*
1%
#216
0%
#217
0*
1%
#218
0%
#219
r100 ,
1*
1'
0)
1%
#220
0%
#221
r0 ,
0*
0'
1%
#222
0%
#223
1*
1)
1%
#224
0%
#225
0*
1'
0)
1%
#226
0%
#227
r100 ,
1*
1)
1%
#228
0%
#229
r0 ,
0*
0'
0)
1%
#230
0%
#231
1*
1)
1%
#232
0%
#233
0*
1'
0)
1%
#234
0%
#235
r100 ,
1*
1)
1%
#236
0%
#237
r0 ,
0*
0'
0)
1%
#238
0%
#239
1*
1)
1%
#240
0%
#241
0*
1'
0)
1%
#242
0%
#243
r100 ,
1*
1)
1%
#244
0%
#245
r0 ,
0*
0'
0)
1%
#246
0%
#247
1*
1)
1%
#248
0%
#249
0*
1'
0)
1%
#250
b10111011 !
b10111011 $
0%
1#
b1011101110111011 &
#251
b10111010 !
b1 (
1*
0'
1)
1%
#252
0%
#253
b10111000 !
b11 (
0*
1'
1%
#254
0%
#255
b10111100 !
b111 (
r100 ,
1*
0)
1%
#256
0%
#257
b10110100 !
b1111 (
r0 ,
0*
1%
#258
0%
#259
b10100100 !
b11111 (
1*
0'
1)
1%
#260
0%
#261
b10000100 !
b111111 (
0*
0)
1%
#262
0%
#263
b11000100 !
b1111111 (
r100 ,
1*
1'
1)
1%
#264
0%
#265
b1000100 !
b11111111 (
r0 ,
0*
0)
1%
#266
0%
#267
r100 ,
1*
1%
#268
0%
#269
r0 ,
0*
1%
#270
0%
#271
r100 ,
1*
1%
#272
0%
#273
r0 ,
0*
1%
#274
0%
#275
r100 ,
1*
1%
#276
0%
#277
r0 ,
0*
1%
#278
0%
#279
r100 ,
1*
1%
#280
0%
#281
r0 ,
0*
1%
#282
0%
#283
r100 ,
1*
1%
#284
0%
#285
r0 ,
0*
1%
#286
0%
#287
r100 ,
1*
1%
#288
0%
#289
r0 ,
0*
1%
#290
0%
#291
r100 ,
1*
1%
#292
0%
#293
r0 ,
0*
1%
#294
0%
#295
r100 ,
1*
1%
#296
0%
#297
r0 ,
0*
1%
#298
0%
#299
r100 ,
1*
1%
